{
  "departments": [
    "Grocery",
    "Health & Beauty",
    "School Supplies",
    "Pets",
    "Household Supplies",
    "Toys",
    "Dairy"
  ],
  "categories": {
    "Grocery": [
      "Breakfast Cereals",
      "Bread",
      "Soups & Mixes",
      "Sauces, Dressings & condiments",
      "Breakfast Spreads",
      "Juices & soft drinks",
      "Snack Bars",
      "Organics",
      "Chocoloates",
      "Energy Drinks",
      "Snacks & Chips",
      "Biscuits & Cookies",
      "Cakes",
      "Tea, Coffee & Hot Drinks",
      "Canned foods",
      "Pasta & Noodles"
    ],
    "Health & Beauty": [
      "cat1",
      "cat2",
      "cat3",
      "cat4",
      "cat5",
      "cat6",
      "cat7",
      "cat8",
      "cat9",
      "cat10",
      "cat11",
      "cat12",
      "cat13",
      "cat14",
      "cat15",
      "cat16"
    ],
    "School Supplies": [
      "Cat1",
      "Cat2",
      "Cat3",
      "Cat4",
      "Cat5",
      "Cat6"
    ],
    "Pets": [
      "Cat_1",
      "Cat_2",
      "Cat_3",
      "Cat_4",
      "Cat_5",
      "Cat_6",
      "Cat_7",
      "Cat_8",
      "Cat_9",
      "Cat_10",
      "Cat_11",
      "Cat_12",
      "Cat_13",
      "Cat_14",
      "Cat_15",
      "Cat_16"
    ],
    "Household Supplies": [
      "category1",
      "category2",
      "category3",
      "category4",
      "category5",
      "category6",
      "category7",
      "category8",
      "category9"
    ],
    "Toys": [],
    "Dairy": []
  }
}